{
  "artifact_level": "unavailable",
  "canonical_url": "https://github.com/zzc-1998/SJTU-H3D",
  "content_sha256": "ddcdc38d067024473f26813756d2ff97921e5724aa2ac65da320210f49384092",
  "creator": "zzc-1998",
  "date_precision": "day",
  "evidence": [
    {
      "kind": "excerpt",
      "locator": "repository description/README",
      "text": "[TIP 2025] Advancing Zero-Shot Digital Human Quality Assessment through Text-Prompted Evaluation # SJTU-H3D Official repo for [\"Advancing Zero-Shot Digital Human Quality Assessment through Text-Prompted Evaluation\"](https://arxiv.org/abs/2307.02808) The database download link is [Onedrive](https://1drv.ms/f/s!AjaDoj_-yWgg7XM5tuQ_Fn3L_WHd?e=2piERr). More info is coming soon!"
    }
  ],
  "platform": "github",
  "provenance": "GitHub repository zzc-1998/SJTU-H3D; discovered by github-repos-07.",
  "published_date": "2023-06-09",
  "publisher": "GitHub",
  "query_ids": [
    "github-repos-07"
  ],
  "rejection_reason": "Relevant discovery held outside the bounded accepted review set; evidence preserved and not counted.",
  "relevance_evidence": [],
  "repository": {
    "full_name": "zzc-1998/SJTU-H3D",
    "last_push": "2023-07-08T06:39:40Z",
    "license": {
      "key": "",
      "name": "",
      "url": ""
    },
    "stars_at_retrieval": 12
  },
  "retrieval_method": "GitHub CLI/API repository search and README endpoint",
  "retrieved_at": "2026-07-12T08:40:05Z",
  "rights_note": "Repository license reported by GitHub: {'key': '', 'name': '', 'url': ''}. Only a bounded README/description span is stored.",
  "rights_status": "open-license",
  "schema_version": 2,
  "source_type": "repository",
  "stable_id": "github-zzc-1998-sjtu-h3d",
  "status": "rejected",
  "title": "zzc-1998/SJTU-H3D"
}
