{
  "artifact_level": "metadata_only",
  "canonical_url": "https://cloud.google.com/blog/topics/customers/how-manipal-hospitals-sped-up-nurse-handoffs-across-37-hospitals",
  "content_sha256": "c0c9924ca984cca0f5a5936df2931d0309d7fed8a4b591da535571d1e335fa31",
  "creator": "cloud.google.com",
  "date_precision": "unknown",
  "evidence": [
    {
      "kind": "excerpt",
      "locator": "public primary page",
      "text": "design:** The solution was not built in a vacuum. The Google team conducted over eight rounds of deep discussion and evaluation sessions directly with our nurses. This ensured the final ISBAR summary format was not just technically impressive, but clinically useful from day one. * **Agile and iterative rollout:** The solution was piloted at one hospital initially to test its performance and safety in a real-world setting. With a successful pilot, the solution is live in 23 of Manipal hospitals, and used by more than 5,000 every day. At full scale, it is projected to help save significant nurse hours on a daily basis. This phased approach, "
    }
  ],
  "platform": "case-studies",
  "provenance": "Primary URL recovered from earlier Exa discovery and citation chasing; catalog query citation-catalog-case-studies.",
  "published_date": null,
  "publisher": "cloud.google.com",
  "query_ids": [
    "citation-catalog-case-studies"
  ],
  "rejection_reason": null,
  "relevance_evidence": [
    "Primary source evidence describes a learning, evaluation, feedback, adaptation, or agentic operating mechanism."
  ],
  "retrieval_method": "agent-reach documented Jina public reader",
  "retrieved_at": "2026-07-12T08:37:34Z",
  "rights_note": "Only a bounded public evidence span is stored; no complete third-party page, PDF, or talk transcript is copied.",
  "rights_status": "bounded-public-evidence",
  "schema_version": 2,
  "source_type": "case-study",
  "stable_id": "case-studies-21813e3f60a2e150",
  "status": "accepted",
  "title": "How Manipal Hospitals sped up nurse handoffs across 37 hospitals"
}
